{
  "db_name": "PostgreSQL",
  "query": "\n            SELECT *\n              FROM movie\n             WHERE name like $1   \n             ORDER BY id\n        ",
  "describe": {
    "columns": [
      {
        "ordinal": 0,
        "name": "id",
        "type_info": "Int4"
      },
      {
        "ordinal": 1,
        "name": "name",
        "type_info": "Varchar"
      },
      {
        "ordinal": 2,
        "name": "status",
        "type_info": "Varchar"
      },
      {
        "ordinal": 3,
        "name": "description",
        "type_info": "Text"
      },
      {
        "ordinal": 4,
        "name": "created_at",
        "type_info": "Timestamp"
      },
      {
        "ordinal": 5,
        "name": "updated_at",
        "type_info": "Timestamp"
      }
    ],
    "parameters": {
      "Left": [
        "Text"
      ]
    },
    "nullable": [
      false,
      false,
      true,
      true,
      true,
      true
    ]
  },
  "hash": "2e160a70c11e85ccb81247a78f104edb5b687bd6706f0be11da60f04f5176972"
}
